Metadata-Version: 1.1
Name: slackweb
Version: 1.0.3
Summary: slack bot for incomming webhook
Home-page: https://github.com/satoshi03/slack-python-webhook
Author: satoshi03
Author-email: innamisatoshi@gmail.com
License: MIT License
Platform: UNKNOWN
Classifier: Programming Language :: Python :: 2.7
Classifier: Programming Language :: Python :: 3
Classifier: Programming Language :: Python :: 3.3
Classifier: License :: OSI Approved :: MIT License
